weather_api/__init__.py
weather_api/weather.py
weather_api/errors/__init__.py
weather_api/errors/errors.py
weather_api/errors/handler.py
weather_api/models/__init__.py
weather_api/models/language.py
weather_api/models/models.py
weather_api/models/responses.py
PyAsyncWeatherAPI-1.0.2.dist-info/LICENSE
PyAsyncWeatherAPI-1.0.2.dist-info/METADATA
PyAsyncWeatherAPI-1.0.2.dist-info/WHEEL
PyAsyncWeatherAPI-1.0.2.dist-info/top_level.txt
PyAsyncWeatherAPI-1.0.2.dist-info/RECORD
