Metadata-Version: 2.1
Name: PyAsyncWeatherAPI
Version: 1.0.2
Summary: Asynchronous api wrapper for www.weatherapi.com!
Home-page: https://github.com/ichetiva/weather-api
Author: @ichetiva
License: gpl-3.0
Keywords: weather,weather-api,api-weather,async-weather,async-weather-api
Platform: UNKNOWN
License-File: LICENSE
